climb_jupyter_igv/__init__.py
climb_jupyter_igv/_version.py
climb_jupyter_igv/exceptions.py
climb_jupyter_igv/handlers.py
climb_jupyter_igv/validators.py
climb_jupyter_igv-0.1.1.data/data/etc/jupyter/jupyter_server_config.d/jupyter_igv.json
climb_jupyter_igv-0.1.1.data/data/share/jupyter/labextensions/climb-jupyter-igv/package.json
climb_jupyter_igv-0.1.1.data/data/share/jupyter/labextensions/climb-jupyter-igv/static/181.06b16152934792150165.js
climb_jupyter_igv-0.1.1.data/data/share/jupyter/labextensions/climb-jupyter-igv/static/937.9ee8ff47f629c9a2423b.js
climb_jupyter_igv-0.1.1.data/data/share/jupyter/labextensions/climb-jupyter-igv/static/988.217948b69b80ebf7cb08.js
climb_jupyter_igv-0.1.1.data/data/share/jupyter/labextensions/climb-jupyter-igv/static/988.217948b69b80ebf7cb08.js.LICENSE.txt
climb_jupyter_igv-0.1.1.data/data/share/jupyter/labextensions/climb-jupyter-igv/static/remoteEntry.14a9c7fe3ecd0ef4eecf.js
climb_jupyter_igv-0.1.1.data/data/share/jupyter/labextensions/climb-jupyter-igv/static/style.js
climb_jupyter_igv-0.1.1.data/data/share/jupyter/labextensions/climb-jupyter-igv/static/third-party-licenses.json
climb_jupyter_igv-0.1.1.data/data/share/jupyter/labextensions/climb-jupyter-igv/install.json
climb_jupyter_igv-0.1.1.dist-info/METADATA
climb_jupyter_igv-0.1.1.dist-info/WHEEL
climb_jupyter_igv-0.1.1.dist-info/licenses/LICENSE
climb_jupyter_igv-0.1.1.dist-info/RECORD
