Metadata-Version: 2.4
Name: climb-jupyter-igv
Version: 0.1.1
Dynamic: Keywords
Summary: JupyterLab extension for IGV
Project-URL: Homepage, https://github.com/CLIMB-TRE/jupyter-igv
Project-URL: Bug Tracker, https://github.com/CLIMB-TRE/jupyter-igv/issues
Project-URL: Repository, https://github.com/CLIMB-TRE/jupyter-igv.git
Author: University of Birmingham
License: MIT License
License-File: LICENSE
Classifier: Framework :: Jupyter
Classifier: Framework :: Jupyter :: JupyterLab
Classifier: Framework :: Jupyter :: JupyterLab :: 3
Classifier: Framework :: Jupyter :: JupyterLab :: 4
Classifier: Framework :: Jupyter :: JupyterLab :: Extensions
Classifier: Framework :: Jupyter :: JupyterLab :: Extensions :: Prebuilt
Classifier: License :: OSI Approved :: BSD License
Classifier: Programming Language :: Python
Classifier: Programming Language :: Python :: 3
Classifier: Programming Language :: Python :: 3.8
Classifier: Programming Language :: Python :: 3.9
Classifier: Programming Language :: Python :: 3.10
Classifier: Programming Language :: Python :: 3.11
Classifier: Programming Language :: Python :: 3.12
Requires-Python: >=3.8
Requires-Dist: boto3
Requires-Dist: climb-jupyter-base
Requires-Dist: jupyter-server<3,>=2.0.1
